llama_index/multi_modal_llms/nebius/__init__.py
llama_index/multi_modal_llms/nebius/base.py
llama_index_multi_modal_llms_nebius-0.5.1.dist-info/METADATA
llama_index_multi_modal_llms_nebius-0.5.1.dist-info/WHEEL
llama_index_multi_modal_llms_nebius-0.5.1.dist-info/licenses/LICENSE
llama_index_multi_modal_llms_nebius-0.5.1.dist-info/RECORD
