Metadata-Version: 2.4
Name: llama-index-multi-modal-llms-nebius
Version: 0.5.1
Summary: llama-index multi-modal-llms nebius ai studio integration
Author-email: Akim Tsvigun <aktsvigun@nebius.com>
License-Expression: MIT
License-File: LICENSE
Requires-Python: <4.0,>=3.9
Requires-Dist: llama-index-core<0.15,>=0.13.0
Requires-Dist: llama-index-embeddings-huggingface<0.7,>=0.6.0
